{
  "Dashboard page section": "xxxxxxxxxxxxxxxxxxxxxxxxxxxxxx",
  "Retour": "Back",
  "Compte Actuel": "Current Account",
  "Tous les comptes": "All Accounts",
  "Dashboard": "Dashboard",
  "Gestion des comptes": "Account Management",
  "Gestion des Utilisateurs": "User Management",
  "Gestion des Groupe": "Group Management",
  "Gestion des Appareils": "Device Management",
  "Gestion des Alertes": "Alert Management",
  "Gestion des Geofences": "Geofence Management",
  "Localisation Appareils": "Device Location",
  "Traduction": "Translation",
  "Déconnexion": "Logout",







  "Dashboard page component": "xxxxxxxxxxxxxxxxxxxxxxxxxxxxxxxxxxxxxxxxxxxxxxxxxxxxxxxxxxxxxxxxxxxxxxx",
  "AccountID": "AccountID",
  "Départ": "Departure",
  "Arrivée": "Arrival",
  "Durée trajet": "Trip Duration",
  "Total": "Total",
  "Inactifs": "Inactive",
  "Actifs": "Active",

  "TableauRecapitulatifComptes": "--------------------------------------------------------",
  "Compte": "Account",
  "Déplacé": "Moved",
  "Hors service": "Out of service",
  "Utilisateur": "User",
  "Groupe": "Group",
  "Geofence": "Geofence",
  "Type": "Type",
  "Manager": "Manager",
  "IsActif": "IsActive",

  "Pas de données disponibles": "No data available",

  "Nom du Groupe": "Group Name",
  "Last Update": "Last Update",
  "Pas de résultat": "No result",

  "Pour Aujourd'hui": "For Today",
  "Statistiques pour aujourd'hui": "Today's Statistics",

  "Code": "Code",
  "Quantité": "Quantity",
  "Description": "Description",
  "Graphe des Comptes": "Accounts Chart",
  "Tableau des Comptes": "Accounts Table",
  "Liste des utilisateurs": "User List",
  "Liste des Groupes": "Group List",
  "Liste des Alertes": "Alert List",
  "Sélectionner un Groupe": "Select a Group",

  "Déplacés": "Moved",
  "Position des appareils": "Device Position",
  "Full Screen": "Full Screen",
  "Nombre d'appareils": "Number of Devices",

  "Nombre de comptes": "Number of Accounts",
  "Tous les appareils": "All Devices",
  "Tableau des comptes": "Accounts Table",
  "Liste des Appareils": "Device List",
  "Voir tous": "View All",
  "Tous les Alertes": "All Alerts",
  "Pas d'adresse disponible": "No Address Available",
  "Adresse": "Address",
  "Account ID": "Account ID",
  "Alerte": "Alert",
  "Last update": "Last update",
  "Chart des Alertes": "Alert Chart",
  "Statut inconnu": "Unknown Status",
  "Tous les Utilisateurs": "All Users",
  "Nom de l'utilisateur": "User Name",
  "Nombre d'appareil": "Number of Devices",
  "Nombre de Groupe": "Number of Groups",
  "Tous les Groupes": "All Groups",









  
  "Code de statut non spécifié": "Unspecified status code",
  "Localisation - En mouvement": "Location - Moving",
  "Localisation - Arrêté": "Location - Stopped",
  "Localisation - Parking": "Location - Parking",
  "Localisation - Odomètre": "Location - Odometer",
  "Localisation - Heures moteur": "Location - Engine hours",
  "Localisation - Niveau de carburant": "Location - Fuel level",
  "Changement d'état d'entrée": "Input state change",
  "Entrée activée": "Input enabled",
  "Entrée désactivée": "Input disabled",
  "Contact allumé": "Ignition on",
  "Contact éteint": "Ignition off",
  "Alimentation activée": "Power on",
  "Alimentation désactivée": "Power off",
  "Batterie faible": "Low battery",
  "Batterie OK": "Battery OK",
  "En charge": "Charging",
  "Non en charge": "Not charging",
  "Détection de remorquage": "Towing detected",
  "Détection de collision": "Collision detected",
  "Excès de vitesse": "Overspeed",
  "Vitesse normale": "Normal speed",
  "Entrée dans une zone géographique": "Geofence entry",
  "Sortie d'une zone géographique": "Geofence exit",
  "Informations de diagnostic": "Diagnostic information",
  "Signal de vie": "Heartbeat",
  "Connexion du conducteur": "Driver connected",
  "Déconnexion du conducteur": "Driver disconnected",
  "Alerte de panique": "Panic alert",
  "Rappel de maintenance": "Maintenance reminder",












  
  "Liste des Comptes": "Accounts List",
  "Veuillez choisir un compte pour continuer": "Please choose an account to continue",
  "Tous les Comptes": "All Accounts",
  "Nom du compte": "Account Name",
  "Nombre d'utilisateur": "Number of Users",
  "Nombre de geozones": "Number of Geozones",
  "Gestion Des Comptes": "Account Management",
  "Ajouter un nouveau Compte": "Add New Account",
  "Nom du Compte": "Account Name",
  "ID du Compte": "Account ID",
  "Nombre d'utilisateurs": "Number of Users",
  "Nombre de Geofences": "Number of Geofences",
  "Date de creation": "Creation Date",
  "Options": "Options",
  "Liste des Utilisateur": "User List",
  "Ajouter": "Add",
  "nouveau utilisateur": "New User",
  "Choisissez un compte": "Choose an Account",
  "Recherche un utilisateur": "Search a User",
  "Nom Utilisateur": "Username",
  "UserID": "User ID",
  "Groupes affectés": "Assigned Groups",
  "Nombre d'Appareils": "Number of Devices",
  "Dernière connexion": "Last Connection",
  "Mot de passe incorrect. Veuillez réessayer": "Incorrect password. Please try again.",
  "Voulez-vous changer de Compte ?": "Do you want to change the Account?",
  "Veuillez entrer votre mot de passe": "Please enter your password",
  "Mot de passe": "Password",
  "Confirmer": "Confirm",
  "Annuler": "Cancel",
  "Mot de passe incorrect": "Incorrect password",
  "Liste des Utilisateurs": "User List",
  "Rechercher un utilisateur": "Search a User",
  "Nombre de Groupes affectés": "Number of Assigned Groups",
  "Voulez-vous Supprimer le groupe ?": "Do you want to delete the group?",
  "Liste des groupes": "Group List",
  "Nouveau Groupe": "New Group",
  "ID du Groupe": "Group ID",
  "Nombre Utilisateurs affectés": "Number of Assigned Users",
  "Voulez-vous Supprimer l'Appareil ?": "Do you want to delete the device?",
  "Nombre Appareils": "Number of Devices",
  "Nouveau Appareil": "New Device",
  "Tous les Appareils": "All Devices",
  "Recherche un appareil": "Search a Device",
  "statut inconnu": "Unknown Status",
  "Pas de nom disponible": "No Name Available",
  "Dernière mise a jour": "Last Update",
  "Code Alerte": "Alert Code",
  "Plaque du véhicule": "Vehicle Plate",
  "Telephone": "Phone",
  "Type d'appareil": "Device Type",
  "ImeiNumber": "IMEI Number",
  "Distance totale parcourue": "Total Distance Traveled",
  "km": "km",
  "Non disponible": "Not Available",
  "Numéro de la carte SIM": "SIM Card Number",
  "Date Creation": "Creation Date",
  "Voir moins": "See Less",
  "Voir plus": "See More",
  "Modifier": "Edit",
  "Supprimer": "Delete",
  "Nombre d'Alerte": "Number of Alerts",
  "Ajouter un Nouveau Geofence": "Add New Geofence",
  "Nouveau Geofence": "New Geofence",
  "Tous les geofences": "All Geofences",
  "Recherche un Groupe": "Search a Group",
  "Nom du Geozone": "Geozone Name",
  "Id du geozone": "Geozone ID",
  "ID du compte": "Account ID",
  "Désactiver": "Disable",
  "le geozone": "the geozone",
  "Êtes-vous sûr de": "Are you sure you want to",
  "Choisissez un véhicule": "Choose a Vehicle",
  "Véhicule non disponible": "Vehicle Not Available",
  "Choisir un véhicule": "Select a Vehicle",
  "Changer le type de vue sur la carte": "Change Map View Type",
  "Type de vue": "View Type",
  "Voir la position géographique de tous les véhicules": "See All Vehicles' Geographic Position",
  "Tous les véhicules": "All Vehicles",
















  
  "Choisissez une langue": "Choose a Language",
  "Français": "French",
  "Espagnol": "Spanish",
  "Anglais": "English",
  "Rechercher un compte": "Search an Account",
  "Cet identifiant (ID) est déjà utilisé. Veuillez en choisir un autre": "This ID is already in use. Please choose another one",
  "L'IMEI doit être un nombre": "IMEI must be a number",
  "Le numéro de la carte SIM doit être un nombre": "SIM card number must be a number",
  "Liste Des Groupe": "Group List",
  "Choisis un ou plusieurs Groupe pour intégrer l'appareil": "Choose one or more Groups to assign the device",
  "Enregistrer un nouveau Appareil": "Register a New Device",
  "Choisissez un Groupe": "Choose a Group",
  "Défaut": "Default",
  "Numéro IMEI": "IMEI Number",
  "IMEI": "IMEI",
  "Description du véhicule": "Vehicle Description",
  "Nom du véhicule": "Vehicle Name",
  "Numéro SIM": "SIM Number",
  "Enregistrer": "Save",
  "Modifier un Appareil": "Edit a Device",
  "Le téléphone n'est pas valide": "Phone number is not valid",
  "L'email de contact n'est pas valide": "Contact email is not valid",
  "L'email de notification n'est pas valide": "Notification email is not valid",
  "Le mot de passe doit contenir au moins 6 caractères": "Password must contain at least 6 characters",
  "Les mots de passe ne correspondent pas": "Passwords do not match",
  "Cet identifiant (accountID) est déjà utilisé. Veuillez en choisir un autre": "This Account ID is already in use. Please choose another one",
  "Activation du compte": "Account Activation",
  "Droit de manager": "Manager Rights",
  "Choisir un TimeZone": "Choose a TimeZone",
  "DisplayName": "Display Name",
  "contactName": "Contact Name",
  "contactEmail": "Contact Email",
  "addressCity": "City",
  "addressCountry": "Country",
  "isActive": "Is Active",
  "Confirmer le mot de passe": "Confirm Password",
  "Ajouter un mot de passe": "Add a Password",
  "Modifier le Compte": "Edit Account",
  "Voulez-vous Supprimer le compte": "Do you want to delete the account?",
  "Options du compte": "Account Options",
  "Gestion des utilisateurs": "User Management",
  "Tous les groupes": "All Groups",
  "Gestion des Groupes": "Group Management",
  "Modifier le compte": "Edit Account",
  "Supprimer le compte": "Delete Account",
  "Le numéro de téléphone est invalide": "Phone number is invalid",
  "Cet identifiant (userID) est déjà utilisé. Veuillez en choisir un autre": "This User ID is already in use. Please choose another one",
  "Choisir un max access level": "Choose Max Access Level",
  "New/Delete": "New/Delete",
  "Read/View": "Read/View",
  "Write/Edit": "Write/Edit",
  "Accès complet": "Full Access",
  "Activation de l'utilisateur": "User Activation",
  "Type de l'utilisateur": "User Type",
  "Utilisateur standard / limité": "Standard / Limited User",
  "Utilisateur Administrateur / Superviseur": "Administrator / Supervisor User",
  "choisissez un role": "Choose a Role",
  "Choisis un Groupe pour intégrer l'appareil": "Choose a Group to assign the device",
  "Ajouter un nouveau Utilisateur": "Add New User",
  "Choisissez un groupe pour affecter l'utilisateur": "Choose a Group to assign the User",
  "Pas de groupe sélectionner": "No Group Selected",
  "ID de l'utilisateur": "User ID",
  "notifyEmail": "Notification Email",
  "TimeZone": "TimeZone",
  "roleID": "Role ID",
  "Modifier l'utilisateur": "Edit User",







  
  "Liste Des Appareils": "Device List",
  "Ajouter un nouveau Groupe": "Add New Group",
  "Choisissez des Appareils pour intégrer dans le groupe": "Choose Devices to Add to the Group",
  "Appareil": "Device",
  "sélectionner": "select",
  "Pas d'appareil sélectionner": "No Device Selected",
  "Description de l'appareil": "Device Description",
  "Notes": "Notes",
  "Ajouter une petite note": "Add a Small Note",
  "Nom de l'appareil": "Device Name",
  "Modifier le Groupe": "Edit Group",
  "Nouvelle position": "New Position",
  "Recommencer": "Restart",
  "Continuer": "Continue",
  "Afficher les geofences dans la carte": "Show Geofences on Map",
  "Oui": "Yes",
  "Non": "No",
  "Ajouter un Geofence": "Add a Geofence",
  "Description de la zone": "Zone Description",
  "Couleur": "Color",
  "Coordonnée": "Coordinate",
  "positions": "positions",
  "Ajouter des position": "Add Positions",
  "Vous devez ajouter au 3 positions": "You Must Add at Least 3 Positions",
  "Choisissez une couleur": "Choose a Color",
  "Bleu foncé": "Dark Blue",
  "Rouge vif": "Bright Red",
  "Vert émeraude": "Emerald Green",
  "Jaune doré": "Golden Yellow",
  "Turquoise": "Turquoise",
  "Violet": "Purple",
  "Orange": "Orange",
  "Gris anthracite": "Charcoal Grey",
  "Rose fuchsia": "Fuchsia Pink",
  "Noir": "Black",
  "accountID": "accountID",
  "Vitesse": "Speed",
  "Statut": "Status",
  "En stationnement": "Parked",
  "En mouvement rapide": "Moving Fast",
  "En mouvement lent": "Moving Slowly",
  "Chargement...": "Loading...",
  "Plaque d'immatriculation": "License Plate",
  "Pas de date disponible": "No Date Available",
  "Voir sur Google Maps": "View on Google Maps",
  "cliquez pour filtrer": "Click to Filter",
  "Véhicules déplacés": "Moved Vehicles",
  "Véhicules non déplacés": "Unmoved Vehicles",
  "Véhicules hors service": "Out-of-Service Vehicles",
  "Rechercher": "Search",
  "Réinitialiser le filtrer par catégorie": "Reset Category Filter",
  "Reset": "Reset",
  "Pas de resultat": "No Results",
  "Choisissez un type de vue": "Choose a View Type",
  "Vue Normale": "Normal View",
  "Vue Satelite": "Satellite View",
  "Vue terrain": "Terrain View",
  "Vue Humanitaire": "Humanitarian View",
  "Vue Claire": "Clear View",
  "Close": "Close",
  "Se Déconnecter": "Log Out",
  "Êtes vous sur de te déconnecter": "Are You Sure You Want to Log Out?",
  "Cancel": "Cancel",
  "Déconnecter": "Log Out",









  
  "Nom absent": "Name Missing",
  "Page d'accueil": "Homepage",
  "Accueil": "Home",
  "Enregistrer un nouveau véhicule": "Register a New Vehicle",
  "Modifier ou Supprimer un Véhicule": "Edit or Delete a Vehicle",
  "Modifier/Supprimer": "Edit/Delete",
  "Voir la position géographique des véhicules": "View Vehicle Locations",
  "Localisation": "Location",
  "Voir tous les détails sur le déplacement d'un véhicule": "View Full Details of Vehicle Movement",
  "Rapport": "Report",
  "Changer en mode sombre ou clair": "Toggle Dark/Light Mode",
  "Mon Profil": "My Profile",
  "Menu": "Menu",
  "Nombre total de véhicules": "Total Number of Vehicles",
  "Véhicules actuellement en service": "Vehicles Currently Active",
  "Véhicules actuellement stationnés": "Vehicles Currently Parked",
  "Véhicules actuellement hors service ou en panne": "Vehicles Currently Out of Service or Broken Down",
  "Hors Service": "Out of Service",
  "Dernière mise à jour": "Last Update",
  "Auto": "Auto",
  "Actualisation auto": "Auto Refresh",
  "Actualisation automatique": "Automatic Refresh",
  "Vous êtes hors ligne. Veuillez vérifier votre connexion internet": "You Are Offline. Please Check Your Internet Connection",
  "Se déconnecter": "Log Out",
  "Mise a jour automatique": "Auto Update",
  "Êtes-vous sur d'activer la mise a jour automatique": "Are You Sure You Want to Enable Auto Update?",
  "Êtes-vous sur de désactiver la mise a jour automatique": "Are You Sure You Want to Disable Auto Update?",
  "Chargement des données": "Loading Data",
  "Adresse non disponible": "Address Unavailable",
  "Aucun véhicule trouvé": "No Vehicle Found",
  "En Stationnement": "Parked",
  "Bloquer le véhicule": "Block Vehicle",
  "Débloquer le véhicule": "Unblock Vehicle",
  "Écouter": "Listen",
  "Attention": "Warning",
  "Vous devez disposer soit de crédits, soit de minutes et SMS disponibles sur votre téléphone pour cette fonctionnalité": "You Must Have Either Credit or Available Minutes and SMS on Your Phone to Use This Feature",
  "Ok": "Ok",
  "Veuillez entrer votre code d'accès": "Please Enter Your Access Code",
  "code d'accès": "Access Code",
  "Voir la position géographique du véhicule": "View Vehicle Location",
  "Voir le trajet du véhicule sur la carte": "View Vehicle Route on the Map",
  "Trajet": "Route",
  "Voir un historique sur l'état du véhicule": "View Vehicle Status History",
  "Historique": "History",
  "Bloquer ou débloquer le véhicule": "Block or Unblock Vehicle",
  "Contrôle": "Control",
  "Voir les informations personnelles du véhicule": "View Vehicle Information",
  "Informations": "Information",
  "Modifier des informations ou supprimer le véhicule": "Edit or Delete Vehicle Information",
  "Modifier ou supprimer l'appareil": "Edit or Delete Device",
  "Mon profil": "My Profile",
  "Ajouter un véhicule": "Add a Vehicle",
  "Modifier ou supprimer un véhicule": "Edit or Delete a Vehicle",
  "Localisation des véhicules": "Vehicle Location",
  "Rapport des véhicules": "Vehicle Report",
  "Gestion des Geozones": "Geozone Management",
  "Gestion des Comptes": "Account Management",
  "Manuel d'utilisation": "User Manual",
  "Profil": "Profile",
  "Arrêtez l'animation": "Stop Animation",
  "Retracer le trajet": "Replay Route",
  "Arrêter": "Stop",
  "Masquer": "Hide",
  "Afficher": "Show",
  "les options": "options",
  "Masquer les options": "Hide Options",
  "Afficher les options": "Show Options",
  "Play": "Play",
  "Pause": "Pause",
  "Activer le centrage automatique de la carte": "Enable Auto-Centering Map",
  "Désactiver le centrage automatique de la carte": "Disable Auto-Centering Map",
  "Recommencer le trajet": "Restart Route",
  "Ajuster la vitesse du trajet": "Adjust Route Speed",
  "Ajuster le niveau de zoom": "Adjust Zoom Level",
  "Voir des details sur le trajet": "View Route Details",
  "Voir les séparations de la carte": "View Map Divisions",
  "Vitesse de l'animation": "Animation Speed",
  "Tres lent": "Very Slow",
  "Lent": "Slow",
  "Normal": "Normal",
  "Rapide": "Fast",
  "Tres rapide": "Very Fast",
  "Super rapide": "Super Fast",
  "Niveau de Zoom lors de l'animation": "Zoom Level During Animation",
  "Centrer automatique la carte lors de l'animation": "Auto-Center Map During Animation",
  "Activer": "Enable",
  "Voir les séparations et le nom des différentes parties de la carte": "Show Map Divisions and Labels",
  "Date": "Date",
  "Heure": "Time",
  "Plaque d’immatriculation": "License Plate",





  
  "Filtrer par Date": "Filter by Date",
  "Filtrer par statut": "Filter by Status",
  "Date et heure de Depart": "Departure Date and Time",
  "Date et heure de d'arrivée": "Arrival Date and Time",
  "Veuillez sélectionner un véhicule": "Please Select a Vehicle",
  "Appliquer": "Apply",
  "Voir l'historique du véhicule": "View Vehicle History",
  "Voir le trajet du véhicule": "View Vehicle Trip",
  "Pas de véhicule sélectionné": "No Vehicle Selected",
  "Voir cette position sur la carte": "View This Location on the Map",
  "Recherche un Geozone": "Search a Geozone",
  "janvier": "January",
  "février": "February",
  "mars": "March",
  "avril": "April",
  "mai": "May",
  "juin": "June",
  "juillet": "July",
  "août": "August",
  "septembre": "September",
  "octobre": "October",
  "novembre": "November",
  "décembre": "December",
  "Rapport des vehicules": "Vehicle Report",
  "All": "All",
  "aujourd'hui": "Today",
  "Véhicules en stationnement": "Parked Vehicles",
  "actuellement": "Currently",
  "Véhicules en mouvement": "Moving Vehicles",
  "Du": "From",
  "au": "to",
  "De": "From",
  "à": "to",
  "Durée": "Duration",
  "Arrivé": "Arrived",
  "Distance": "Distance",
  "Trajet du véhicule": "Vehicle Trip",
  "Trajet du véhicule ici": "Vehicle Trip Here",
  "Tableau des deplacements": "Movement Table",
  "Véhicule": "Vehicle",
  "Date et Heure de départ": "Departure Date and Time",
  "Date et Heure d'arrivée": "Arrival Date and Time",
  "Adresse de départ": "Departure Address",
  "Adresse d'arrivée": "Arrival Address",
  "Pas de dépacement": "No Movement",
  "Tableau des Distances": "Distance Table",
  "Tableau des activites": "Activity Table",
  "Duree du trajet": "Trip Duration",
  "Tableau des vitesse": "Speed Table",
  "Vitesse maximale": "Maximum Speed",
  "Vitesse minimale": "Minimum Speed",
  "Vitesse moyenne": "Average Speed",
  "Tableau du trajet": "Trip Table",
  "Temps d'activité": "Activity Time",
  "Temps d'inactivité": "Idle Time",
  "Distance parcourue": "Distance Traveled",
  "Nombre d'arrêt": "Number of Stops",
  "arrêt": "stop",
  "Rapport détaillé en groupe": "Detailed Group Report",
  "Informations sur les véhicules": "Vehicle Information",
  "Date de recherche trouvée": "Search Date Found",
  "Informations Actuellement": "Current Information",
  "voir": "view",
  "Véhicule en mouvement": "Moving Vehicle",
  "Véhicule en stationnement": "Parked Vehicle",
  "Véhicule hors service": "Out-of-Service Vehicle",
  "Pour la journée d'aujourd'hui": "For Today",
  "Véhicule en mouvement en 1er": "First Moving Vehicle",
  "Le": "The",
  "Pas de véhicule en mouvement": "No Moving Vehicle",
  "Voir sur la carte": "View on Map",
  "Plus d'info": "More Info",
  "Véhicule ayant parcouru la plus grande distance": "Vehicle with Longest Distance Traveled",
  "environ": "about",
  "Véhicule en mouvement plus longtemps": "Vehicle in Motion Longest",
  "Véhicule avec la vitesse maximale": "Vehicle with Maximum Speed",
  "voir moins": "see less",
  "Informations sur le trajet des véhicules": "Vehicle Trip Information",
  "Temps d'activité total": "Total Activity Time",
  "Nombre total d’arrêts": "Total Number of Stops",
  "arrêts": "stops",
  "Position des véhicules": "Vehicle Positions",
  "Tableau récapitulatif": "Summary Table",
  "Filtrer": "Filter",
  "Filtrer par": "Filter by",
  "Croissant": "Ascending",
  "Décroissant": "Descending",
  "Heure de départ": "Departure Time",
  "Distance parcouru": "Distance Traveled",
  "Temps en mouvement": "Time in Motion",
  "Télécharger": "Download",
  "Nombre d'arrêts": "Number of Stops",
  "Distance totale": "Total Distance",
  "Date du résultat": "Result Date",
  "Heure du résultat": "Result Time",
  "Voir cette adresse sur la carte": "View This Address on the Map",
  "Rapport détaillé du véhicule": "Detailed Vehicle Report",
  "Informations sur le véhicule": "Vehicle Info",
  "Heure de recherche trouvée": "Search Time Found",
  "Pas d'heure disponible": "No Time Available",
  "Heure d'arrivée": "Arrival Time",
  "Pas de mouvement": "No Movement",
  "Durée total en mouvement": "Total Time in Motion",
  "Durée des arrêts lors du déplacement": "Stop Duration During Travel",
  "Duree de l’arrêts le plus long": "Longest Stop Duration",
  "Graphe des vitesses": "Speed Graph",
  "Recherche": "Search",
  "Voir l’historique": "View History",
  "Tous les lieux fréquentés": "All Visited Places",
  "Tous les lieux Stationnés": "All Parking Places",
  "Filtre en ordre croissant": "Ascending Filter",
  "Filtre en ordre décroissant": "Descending Filter",















  
  "Tables des véhicules": "Vehicle Tables",
  "Rapport personnel": "Personal Report",
  "Rapport en Groupe": "Group Report",
  "Rapport Tableau Récapitulatif en Groupe": "Group Summary Table Report",
  "Rapport en groupe": "Group Report",
  "Télécharger en PDF": "Download as PDF",
  "Unite": "Unit",
  "Le téléchargement peut prendre jusqu'a 1 minute": "Download may take up to 1 minute",
  "Télécharger le rapport en PDF": "Download Report as PDF",
  "Télécharger le tableau récapitulatif en PDF": "Download Summary Table as PDF",
  "Télécharger le tableau récapitulatif en Exel": "Download Summary Table as Excel",
  "Recherche par date": "Search by Date",
  "Recherche par intervalle de date": "Search by Date Range",
  "Sélectionner une intervalle de date": "Select a Date Range",
  "Recherche pour une journée": "Search for One Day",
  "Sélectionner une date": "Select a Date",
  "Le mot de passe est incorrect. Veuillez réessayer": "Incorrect Password. Please Try Again",
  "Nom d'utilisateur": "Username",
  "Fuseau horaire": "Time Zone",
  "Version de l'application": "App Version",
  "Redémarrer l'application": "Restart the Application",
  "Cliquez ici": "Click Here",
  "Êtes vous sur de redémarrer l'application": "Are You Sure You Want to Restart the Application?",








  
  "Voir un rapport pour un seul véhicule": "View a Report for a Single Vehicle",
  "Unité": "Unit",
  "Voir un rapport pour tous les véhicules": "View a Report for All Vehicles",
  "Gestion des Roles": "Role Management",
  "Language": "Language",
  "Bienvenue à Octagono Plus": "Welcome to Octagono Plus",
  "Pays": "Country",
  "Sélectionner un pays": "Select a Country",
  "Haïti": "Haiti",
  "République Dominicaine": "Dominican Republic",
  "Se souvenir de moi": "Remember Me",
  "Chargement": "Loading",
  "Se connecter": "Sign In",
  "Compte Demo": "Demo Account",







  
  "Sélectionner une langue": "Select a Language",
  "Creation du nouveau groupe avec succès": "New Group Created Successfully",
  "Échec de la Creation du groupe": "Failed to Create Group",
  "Modification du groupe avec succès": "Group Updated Successfully",
  "Échec de la Modification du groupe": "Failed to Update Group",
  "Suppression du groupe avec succès": "Group Deleted Successfully",
  "Échec de la Suppression du groupe": "Failed to Delete Group",
  "Creation du nouveau utilisateur avec succès": "New User Created Successfully",
  "Échec de la Creation du l'utilisateur": "Failed to Create User",
  "Modification de l'utilisateur avec succès": "User Updated Successfully",
  "Échec de la Modification de l'utilisateur": "Failed to Update User",
  "Suppression de l'utilisateur avec succès": "User Deleted Successfully",
  "Échec de Suppression de l'utilisateur": "Failed to Delete User",
  "Creation du nouveau compte avec succès": "New Account Created Successfully",
  "Échec de la Creation du compte": "Failed to Create Account",
  "Compte modifié avec succès": "Account Updated Successfully",
  "Échec de la  Modification du compte": "Failed to Update Account",
  "Compte supprimer avec succès": "Account Deleted Successfully",
  "Échec de Suppression du compte": "Failed to Delete Account",
  "Creation du nouveau appareil avec succès": "New Device Created Successfully",
  "Échec de la Creation de l'appareil": "Failed to Create Device",
  "Modification de l'appareil avec succès": "Device Updated Successfully",
  "Échec de la modification de l'appareil": "Failed to Update Device",
  "Suppression de l'appareil avec succès": "Device Deleted Successfully",
  "Échec de Suppression de l'appareil": "Failed to Delete Device",
  "Vous avez ajoutee le geofence avec succès": "Geofence Added Successfully",
  "Échec de l'ajout du Geofence": "Failed to Add Geofence",
  "Modification du geofence avec succès": "Geofence Updated Successfully",
  "Échec de la modification du geofence": "Failed to Update Geofence",
  "Suppression du geofence avec succès": "Geofence Deleted Successfully",
  "Échec de la Suppression du geofence": "Failed to Delete Geofence",
  "Échec de la Modification du geofence": "Failed to Update Geofence",
  "Vous avez ajouté l'appareil avec succès": "Device Added Successfully",
  "Échec de l'ajout du véhicule": "Failed to Add Vehicle",
  "Vous avez modifié le véhicule avec succès": "Vehicle Updated Successfully",
  "Échec de la modification du véhicule": "Failed to Update Vehicle",
  "Vous avez supprimé le véhicule avec succès": "Vehicle Deleted Successfully",
  "Échec de la suppression du véhicule": "Failed to Delete Vehicle",



  
  "Low Battery": "Low Battery",
  "In motion": "In Motion",
  "Panic": "Panic",
  "Ignition OFF": "Ignition OFF",
  "Ignition ON": "Ignition ON",
  "Arrived at Geozone": "Arrived at Geozone",
  "Aucun": "None",
  "Ajouter un nouveau Role": "Add New Role",
  "Rechercher un Role": "Search Role",
  "Gestion Des Role": "Role Management",
  "Pas de compte sélectionner": "No Account Selected",
  "deviceID": "deviceID",
  "Tous": "All",
  "Choisissez un Appareil": "Choose a Device",
  "imeiNumber": "IMEI Number",
  "groupID": "groupID",
  "ruleID": "ruleID",
  "selector": "selector",
  "emailSubject": "Email Subject",
  "emailText": "Email Text",
  "Activation": "Activation",
  "Veuillez choisir un compte": "Please Select an Account",
  "Le champ selector est vide": "The Selector Field is Empty",
  "Historique d'un Appareils": "Device History",
  "Trajet d'un Appareils": "Device Trip",
  "Informations sur un Appareils": "Device Information",
  "Admin Dashboard": "Admin Dashboard",
  "Mode Utilisateur": "User Mode",
  "Rapport Groupe": "Group Report",
  "Rapport Unite": "Unit Report",
  "Options de l'appareil": "Device Options",
  "Localisation de l'appareil": "Device Location",
  "Trajet de l'appareil": "Device Trip",
  "Historique de l'appareil": "Device History",
  "Rapport de l'appareil": "Device Report",
  "Contrôle de l'appareil": "Device Control",
  "Informations sur l'appareil": "Device Information",
  "Modifier l'appareil": "Edit Device",
  "Supprimer l'appareil": "Delete Device",
  "Mettre a jour les donnees": "Update Data",
  "Informations Generale": "General Information",
  "Information sur les déplacements": "Movement Information",
  "Comptes": "Accounts",
  "Utilisateurs": "Users",
  "Appareils": "Devices",
  "sysadmin Dashboard": "Sysadmin Dashboard",



  
  "Session inactive": "Inactive session",
  "Inactivité de 30 minutes détectée. Veuillez confirmer votre mot de passe pour continuer": "30 minutes of inactivity detected. Please confirm your password to continue",
  "Confirmer ton Mot de passe": "Confirm your password",
  "Application déjà installée": "Application already installed",
  "Installation non supportée": "Installation not supported",
  "Installation non disponible": "Installation not available",
  "Installer l'application": "Install the application",
  "Installation en cours": "Installation in progress",
  "Appareils Actifs": "Active Devices",
  "Appareils Inactifs": "Inactive Devices",
  "Appareils En déplacement": "Devices in Motion",
  "Appareils Déplacer": "Moving Devices",
  "Voulez-vous Supprimer l'utilisateur": "Do you want to delete the user",
  "Options de l'utilisateur": "User Options",
  "Groupe affecté": "Assigned Group",
  "Supprimer l'utilisateur": "Delete User",
  "Login": "Login",
  "Nombre Appareil": "Number of Devices",
  "Adresse du véhicule": "Vehicle Address",
  "Statut du véhicule": "Vehicle Status",
  "Veuillez choisir un véhicule": "Please choose a vehicle",
  "Choisir": "Choose",
  "En Déplacement": "In Motion",





  
  "Véhicules En déplacement": "Vehicles in Motion",
  "Il n’est pas possible de fournir un rapport global pour tous": "It is not possible to provide a global report for all.",
  "Ce compte comprend plus de 50 appareils": "This account includes more than 50 devices",
  "Documentation": "Documentation",
  "ID du geofence": "Geofence ID",
  "Nombre de coordonnées": "Number of Coordinates",
  "Choisissez une date et une heure": "Choose a Date and Time",
  "Une recherche portant sur plus de 3 jours ralentira un peu la carte": "A search of more than 3 days will slightly slow down the map",
  "Date de Début": "Start Date",
  "Choisissez une date": "Choose a Date",
  "Heure de Début": "Start Time",
  "Date de Fin": "End Date",
  "Heure de fin": "End Time",
  "Page non trouvée": "Page Not Found",
  "Oups ! La page que vous recherchez n'existe pas": "Oops! The page you are looking for does not exist",
  "Retour à l'accueil": "Back to Home",
  "Si vous pensez qu'il s'agit d'une erreur, veuillez contacter le support": "If you think this is an error, please contact support",





  
  "Le processus peut prendre un peu de temps selon le nombre de véhicules, mais reste rapide.": "The process may take a little time depending on the number of vehicles, but it remains fast.",
  "Notez bien": "Please note",
  "Voir plus de Résultat": "See more results",

  "Résultat": "Result",
  "Recherche une alerte": "Search for an alert",
  "Appareils non déplacés": "Non-moved devices",
  "Appareils en Stationnement": "Devices in Parking",
  "Non Déplacer": "Not Moved",
  "Appareils Déplacés": "Moved Devices",
  "Statistiques par compte": "Statistics by Account",

"Nombre appareils": "Number of devices",




  "Options du groupe": "Group options",
  "Afficher Les Appareils": "Show devices",
  "Liste des utilisateurs affectés": "List of assigned users",
  "Liste Les Appareils": "Device list",
  "Modifier le groupe": "Edit group",
  "Supprimer le groupe": "Delete group",
  "Rechercher une option": "Search for an option",
  "Veuillez cliquer sur l'option de l'utilisateur a modifier, puis sur 'Modifier l'utilisateur'": "Please click on the user option to modify, then on 'Edit user'",
  "Veuillez cliquer sur l'option du groupe a modifier, puis sur 'Modifier le groupe'": "Please click on the group option to modify, then on 'Edit group'",
  "Veuillez cliquer sur l'option de l'appareil a modifier, puis sur 'Modifier l'appareil'": "Please click on the device option to modify, then on 'Edit device'",
  "Veuillez cliquer sur le bouton 'Modifier' du geofence souhaité modifier": "Please click on the 'Edit' button of the geofence you want to modify",

  "Informations utilisateur": "User information",

  "Ajouter un nouveau compte": "Add a new account",
  "Modifier un compte": "Edit an account",
  "Supprimer un compte": "Delete an account",

  "Ajouter un nouveau utilisateur": "Add a new user",
  "Modifier un utilisateur": "Edit a user",
  "Supprimer un utilisateur": "Delete a user",

  "Gestion des groupes": "Group management",
  "Ajouter un nouveau groupe": "Add a new group",
  "Modifier un groupe": "Edit a group",
  "Supprimer un groupe": "Delete a group",

  "Gestion des appareils": "Device management",
  "Ajouter un nouveau appareil": "Add a new device",
  "Modifier un appareil": "Edit a device",
  "Supprimer un appareil": "Delete a device",

  "Gestion des geofences": "Geofence management",
  "Ajouter une nouvelle geozone": "Add a new geofence",
  "Modifier une geozone": "Edit a geofence",
  "Supprimer une geozone": "Delete a geofence",


"succès": "succès",
"échec": "failed",
"Échec": "Failed",


"Veuillez ajouter au moins 3 positions": "Please add at least 3 positions",
"Veuillez ajouter une description": "Please add a description",
"Choisir une couleur": "Choose a color",
"Modifier Geofence": "Edit Geofence",
"Créer Geofence": "Create Geofence",
"Marqueur": "Marker",
"Coordonnées": "Coordinates",



"Ce nom de Geozone existe deja": "This Geozone name already exists",
"Liste des appareils de": "Device list of"








  











}
